youtube_music_wrapper_api/__init__.py
youtube_music_wrapper_api/api_calls.py
youtube_music_wrapper_api/http_calls.py
youtube_music_wrapper_api-0.0.1.dist-info/METADATA
youtube_music_wrapper_api-0.0.1.dist-info/WHEEL
youtube_music_wrapper_api-0.0.1.dist-info/licenses/LICENSE.md
youtube_music_wrapper_api-0.0.1.dist-info/RECORD
